finite_time_optim/__init__.py
finite_time_optim/finite_time_momentum.py
finite_time_optim/finite_time_normalized_gradient.py
finite_time_optim/finite_time_sign_gradient.py
finite_time_optim/test_optimizer.py
finite_time_optim-0.1.0.dist-info/METADATA
finite_time_optim-0.1.0.dist-info/WHEEL
finite_time_optim-0.1.0.dist-info/top_level.txt
finite_time_optim-0.1.0.dist-info/RECORD
